lima_api/__init__.py
lima_api/config.py
lima_api/constants.py
lima_api/core.py
lima_api/exceptions.py
lima_api/parameters.py
lima_api/retry_processors.py
lima_api/utils.py
lima_api/code_generator/__init__.py
lima_api/code_generator/cli_gen.py
lima_api/code_generator/main.py
lima_api/code_generator/schemas.py
lima_api/code_generator/templates.py
lima_api/code_generator/utils.py
lima_api-1.4.3.dist-info/licenses/LICENSE
lima_api-1.4.3.dist-info/METADATA
lima_api-1.4.3.dist-info/WHEEL
lima_api-1.4.3.dist-info/entry_points.txt
lima_api-1.4.3.dist-info/top_level.txt
lima_api-1.4.3.dist-info/RECORD
