Metadata-Version: 2.4
Name: lima-api
Version: 1.4.3
Summary: Lima-API is sync and async library that allows implements Rest APIs libs with python typing.
Author: Cesar Gonzalez
Author-email: Victor Torre <vatorre@paradigmadigital.com>
License: MIT License
Classifier: License :: OSI Approved :: MIT License
Classifier: Intended Audience :: Developers
Classifier: Programming Language :: Python :: 3
Classifier: Operating System :: OS Independent
Classifier: Topic :: Software Development :: Libraries :: Python Modules
Requires-Python: >=3.9
License-File: LICENSE
Requires-Dist: httpx
Requires-Dist: opentelemetry-instrumentation-httpx
Provides-Extra: test
Requires-Dist: coverage; extra == "test"
Requires-Dist: pytest; extra == "test"
Requires-Dist: pytest-cov; extra == "test"
Requires-Dist: pytest-mock; extra == "test"
Requires-Dist: pytest-httpserver; extra == "test"
Requires-Dist: freezegun; extra == "test"
Requires-Dist: ruff; extra == "test"
Requires-Dist: uv; extra == "test"
Requires-Dist: opentelemetry-sdk; extra == "test"
Provides-Extra: pydantic2
Requires-Dist: pydantic[email]<3.0,>=2.3.0; extra == "pydantic2"
Requires-Dist: pydantic-settings>=2.0.3; extra == "pydantic2"
Provides-Extra: pydantic1
Requires-Dist: pydantic[email]<2.0,>=1.10; extra == "pydantic1"
Provides-Extra: docs
Requires-Dist: sphinx>=7.0.0; extra == "docs"
Requires-Dist: myst-parser>=2.0.0; extra == "docs"
Requires-Dist: sphinx_design>=0.5.0; extra == "docs"
Requires-Dist: pydata-sphinx-theme>=0.14.0; extra == "docs"
Provides-Extra: all
Requires-Dist: lima-api[docs,pydantic2,test]; extra == "all"
Dynamic: license-file
